xapipy/__init__.py
xapipy/xapipy.py
xapipy-0.1.0.dist-info/licenses/LICENSE.txt
xapipy-0.1.0.dist-info/METADATA
xapipy-0.1.0.dist-info/WHEEL
xapipy-0.1.0.dist-info/top_level.txt
xapipy-0.1.0.dist-info/RECORD
